{
  "task_id": "hello-world-api",
  "task_name": "Unknown Task",
  "validation_time": "2026-01-14T17:17:01.917467",
  "status": "failed",
  "checks": [
    {
      "check": "file_exists",
      "status": "passed",
      "message": "Target file exists: flow_code/hello_api.py"
    }
  ],
  "errors": [
    {
      "type": "python_import",
      "message": "Python import failed: No module named 'flask'",
      "severity": "error",
      "traceback": "Traceback (most recent call last):\n  File \"/home/runner/work/flow-tasks/flow-tasks/process_tasks.py\", line 119, in validate_task_implementation\n    module_spec.loader.exec_module(task_module)\n  File \"<frozen importlib._bootstrap_external>\", line 883, in exec_module\n  File \"<frozen importlib._bootstrap>\", line 241, in _call_with_frames_removed\n  File \"/home/runner/work/flow-tasks/flow-tasks/flow_code/hello_api.py\", line 8, in <module>\n    from flask import Flask, jsonify\nModuleNotFoundError: No module named 'flask'\n"
    }
  ],
  "warnings": [],
  "metrics": {
    "execution_time_ms": 1.89,
    "files_checked": 1,
    "lines_of_code": 36
  },
  "metadata": {
    "description": "寫一個 Flask 的 hello world API，輸出 \"你好，世界\"",
    "priority": "medium",
    "tags": []
  }
}